[
  {
    "position": [15, 0.12, 547],
    "title": "Linkedin",
    "link": "https://linkedin.com/in/emanuele-zini",
    "component": "LinkedinLogo"
  },
  {
    "position": [-15, 0.12, 557],
    "title": "Github",
    "link": "https://github.com/Gr3it",
    "component": "GithubLogo"
  },
  {
    "position": [15, 0.12, 571],
    "title": "Email",
    "link": "mailto:emanuele.zini11+work@gmail.com",
    "component": "PaperPlaneLogo"
  },
  {
    "position": [-15, 0.12, 581],
    "title": "CV",
    "document": "Emanuele Zini CV.pdf",
    "component": "DocumentLogo"
  }
]
